libexamplepy/MyClass.py
libexamplepy/__init__.py
libexamplepy-0.0.1.dist-info/METADATA
libexamplepy-0.0.1.dist-info/WHEEL
libexamplepy-0.0.1.dist-info/top_level.txt
libexamplepy-0.0.1.dist-info/RECORD
