Metadata-Version: 2.1
Name: libexamplepy
Version: 0.0.1
Summary: My First Library
Author: MyName
License: MIT
